AUTHORS.rst
CONTRIBUTING.rst
HISTORY.rst
LICENSE
MANIFEST.in
README.rst
setup.cfg
setup.py
docs/Makefile
docs/api_reference.rst
docs/authors.rst
docs/conf.py
docs/contributing.rst
docs/history.rst
docs/index.rst
docs/make.bat
docs/overview.rst
docs/readme.rst
docs/usage.rst
docs/guide/connecting.rst
docs/guide/defining-entities.rst
docs/guide/flask.rst
docs/guide/index.rst
docs/guide/installation.rst
gcloud_odm/__init__.py
gcloud_odm/datastore_client.py
gcloud_odm/model.py
gcloud_odm/types.py
gcloud_odm.egg-info/PKG-INFO
gcloud_odm.egg-info/SOURCES.txt
gcloud_odm.egg-info/dependency_links.txt
gcloud_odm.egg-info/not-zip-safe
gcloud_odm.egg-info/requires.txt
gcloud_odm.egg-info/top_level.txt
gcloud_odm/contrib/__init__.py
gcloud_odm/contrib/flask.py
tests/__init__.py
tests/test_gcloud_datastore_odm.py