Metadata-Version: 1.1
Name: gcloud-odm
Version: 0.0.4
Summary: Google cloud datastore based ODM
Home-page: https://github.com/fulfilio/gcloud_odm
Author: Fulfil.io Inc.
Author-email: support@fulfil.io
License: BSD license
Keywords: gcloud_odm
Platform: UNKNOWN
Classifier: Development Status :: 2 - Pre-Alpha
Classifier: Intended Audience :: Developers
Classifier: License :: OSI Approved :: BSD License
Classifier: Natural Language :: English
Classifier: Programming Language :: Python :: 2
Classifier: Programming Language :: Python :: 2.6
Classifier: Programming Language :: Python :: 2.7
Classifier: Programming Language :: Python :: 3
Classifier: Programming Language :: Python :: 3.3
Classifier: Programming Language :: Python :: 3.4
Classifier: Programming Language :: Python :: 3.5
